molecule/__init__.py
molecule/__main__.py
molecule/_version.py
molecule/ansi_output.py
molecule/api.py
molecule/app.py
molecule/click_cfg.py
molecule/compatibility.py
molecule/config.py
molecule/console.py
molecule/constants.py
molecule/exceptions.py
molecule/interpolation.py
molecule/logger.py
molecule/platforms.py
molecule/py.typed
molecule/scenario.py
molecule/scenarios.py
molecule/shell.py
molecule/state.py
molecule/status.py
molecule/text.py
molecule/types.py
molecule/util.py
molecule/command/__init__.py
molecule/command/base.py
molecule/command/check.py
molecule/command/cleanup.py
molecule/command/converge.py
molecule/command/create.py
molecule/command/dependency.py
molecule/command/destroy.py
molecule/command/drivers.py
molecule/command/idempotence.py
molecule/command/list.py
molecule/command/login.py
molecule/command/matrix.py
molecule/command/prepare.py
molecule/command/reset.py
molecule/command/side_effect.py
molecule/command/syntax.py
molecule/command/test.py
molecule/command/verify.py
molecule/command/init/__init__.py
molecule/command/init/base.py
molecule/command/init/init.py
molecule/command/init/scenario.py
molecule/data/__init__.py
molecule/data/driver.json
molecule/data/init-scenario.yml
molecule/data/molecule.json
molecule/data/templates/scenario/converge.yml.j2
molecule/data/templates/scenario/create.yml.j2
molecule/data/templates/scenario/destroy.yml.j2
molecule/data/templates/scenario/molecule.yml.j2
molecule/data/templates/scenario/verify.yml.j2
molecule/dependency/__init__.py
molecule/dependency/base.py
molecule/dependency/shell.py
molecule/dependency/ansible_galaxy/__init__.py
molecule/dependency/ansible_galaxy/base.py
molecule/dependency/ansible_galaxy/collections.py
molecule/dependency/ansible_galaxy/roles.py
molecule/driver/__init__.py
molecule/driver/base.py
molecule/driver/delegated.py
molecule/model/__init__.py
molecule/model/schema_v3.py
molecule/provisioner/__init__.py
molecule/provisioner/ansible.py
molecule-25.11.0.dist-info/licenses/LICENSE
molecule-25.11.0.dist-info/METADATA
molecule-25.11.0.dist-info/WHEEL
molecule-25.11.0.dist-info/entry_points.txt
molecule-25.11.0.dist-info/top_level.txt
molecule-25.11.0.dist-info/RECORD
