Metadata-Version: 2.4
Name: molecule
Version: 25.11.0
Summary: Molecule aids in the development and testing of Ansible roles
Author-email: Ansible by Red Hat <info@ansible.com>
Maintainer-email: Ansible by Red Hat <info@ansible.com>
License-Expression: MIT
Project-URL: changelog, https://github.com/ansible-community/molecule/releases
Project-URL: documentation, https://molecule.readthedocs.io/
Project-URL: homepage, https://github.com/ansible-community/molecule
Project-URL: repository, https://github.com/ansible-community/molecule
Keywords: ansible,molecule,roles,testing
Classifier: Development Status :: 5 - Production/Stable
Classifier: Environment :: Console
Classifier: Intended Audience :: Developers
Classifier: Intended Audience :: Information Technology
Classifier: Intended Audience :: System Administrators
Classifier: Operating System :: MacOS
Classifier: Operating System :: POSIX
Classifier: Programming Language :: Python
Classifier: Programming Language :: Python :: 3
Classifier: Programming Language :: Python :: 3.10
Classifier: Programming Language :: Python :: 3.11
Classifier: Programming Language :: Python :: 3.12
Classifier: Programming Language :: Python :: 3.13
Classifier: Topic :: Software Development :: Bug Tracking
Classifier: Topic :: Software Development :: Quality Assurance
Classifier: Topic :: Software Development :: Testing
Classifier: Topic :: System :: Systems Administration
Classifier: Topic :: Utilities
Requires-Python: >=3.10
License-File: LICENSE
Requires-Dist: ansible-compat>=25.1.4
Requires-Dist: ansible-core>=2.15.0
Requires-Dist: click<9,>=8.0
Requires-Dist: click-help-colors>=0.9.4
Requires-Dist: enrich>=1.2.7
Requires-Dist: jinja2>=2.11.3
Requires-Dist: jsonschema>=4.9.1
Requires-Dist: packaging>=25.0
Requires-Dist: pluggy<2.0,>=0.7.1
Requires-Dist: pyyaml>=5.1
Requires-Dist: rich>=9.5.1
Requires-Dist: wcmatch>=8.1.2
Dynamic: license-file
